{
  "groups": [
    {
      "title": "Default Content",
      "id": "default",
      "components": [
        {
          "title": "Text",
          "id": "text",
          "plugins": {
            "da": {
              "name": "text",
              "type": "text"
            }
          }
        },
        {
          "title": "Image",
          "id": "image",
          "plugins": {
            "da": {
              "name": "image",
              "type": "image"
            }
          }
        }
      ]
    },
    {
      "title": "Sections",
      "id": "sections",
      "components": [
        {
          "title": "Section",
          "id": "section",
          "plugins": {
            "da": {
              "unsafeHTML": "<div></div>"
            }
          },
          "filter": "section",
          "model": "section"
        }
      ]
    },
    {
      "title": "Blocks",
      "id": "blocks",
      "components": [
        {
          "title": "Accordion",
          "id": "accordion",
          "model": "accordion",
          "filter": "accordion",
          "plugins": {
            "da": {
              "name": "accordion",
              "rows": 1,
              "columns": 2
            }
          }
        },
        {
          "title": "Accordion Item",
          "id": "accordion-item",
          "model": "accordion-item",
          "plugins": {
            "da": {
              "name": "accordion-item",
              "rows": 2,
              "columns": 0,
              "fields": [
                {
                  "name": "summary",
                  "selector": "div:nth-child(1)"
                },
                {
                  "name": "text",
                  "selector": "div:nth-child(2)"
                }
              ]
            }
          }
        },
        {
          "title": "Cards",
          "id": "cards",
          "model": "cards",
          "filter": "cards",
          "plugins": {
            "da": {
              "rows": 1,
              "columns": 2
            }
          }
        },
        {
          "title": "Card",
          "id": "card",
          "model": "card",
          "plugins": {
            "da": {
              "rows": 1,
              "columns": 2,
              "fields": [
                {
                  "name": "image",
                  "selector": "div:nth-child(1)>picture>img[src]"
                },
                {
                  "name": "imageAlt",
                  "selector": "div:nth-child(1)>picture>img[alt]"
                },
                {
                  "name": "text",
                  "selector": "div:nth-child(2)"
                }
              ]
            }
          }
        },
        {
          "title": "Catalog Highlights",
          "id": "catalog-highlights",
          "model": "catalog-highlights",
          "plugins": {
            "da": {
              "name": "catalog-highlights",
              "rows": 1,
              "columns": 8
            }
          }
        },
        {
          "title": "Carousel",
          "id": "carousel",
          "model": "carousel",
          "filter": "carousel",
          "plugins": {
            "da": {
              "rows": 1,
              "columns": 2
            }
          }
        },
        {
          "title": "Carousel Slide",
          "id": "carousel-item",
          "model": "carousel-item",
          "plugins": {
            "da": {
              "rows": 1,
              "columns": 2,
              "fields": [
                {
                  "name": "backgroundImage",
                  "selector": "div:nth-child(1)>picture>img[src]"
                },
                {
                  "name": "backgroundImageAlt",
                  "selector": "div:nth-child(1)>picture>img[alt]"
                },
                {
                  "name": "text",
                  "selector": "div:nth-child(2)"
                }
              ]
            }
          }
        },
        {
          "title": "Columns",
          "id": "columns",
          "model": "columns",
          "filter": "columns",
          "plugins": {
            "da": {
              "name": "columns",
              "rows": 1,
              "columns": 2,
              "behaviour": "columns"
            }
          }
        },
        {
          "title": "Columns Row",
          "id": "columns-row",
          "model": "columns-row",
          "filter": "columns-row",
          "plugins": {
            "da": {
              "name": "columns-row",
              "behaviour": "columns-row"
            }
          }
        },
        {
          "title": "Columns Cell",
          "id": "columns-cell",
          "model": "columns-cell",
          "filter": "columns-cell",
          "plugins": {
            "da": {
              "unsafeHTML": "<div></div>",
              "behaviour": "columns-cell"
            }
          }
        },
        {
          "title": "Fragment",
          "id": "fragment",
          "model": "fragment",
          "plugins": {
            "da": {
              "rows": 1,
              "columns": 1,
              "fields": [
                {
                  "name": "fragmentUrl",
                  "selector": "div>div>p>a[href]"
                },
                {
                  "name": "fragmentUrlText",
                  "selector": "div>div>p>a"
                }
              ]
            }
          }
        },
        {
          "title": "Form MCCS Preferences",
          "id": "form-mccs-preferences",
          "plugins": {
            "da": {
              "name": "form-mccs-preferences",
              "rows": 3,
              "columns": 1
            }
          }
        },
        {
          "title": "Hero",
          "id": "hero",
          "model": "hero",
          "plugins": {
            "da": {
              "rows": 1,
              "columns": 1,
              "fields": [
                {
                  "name": "image",
                  "selector": "div>div>picture>img[src]"
                },
                {
                  "name": "alt",
                  "selector": "div>div>picture>img[alt]"
                },
                {
                  "name": "text",
                  "selector": "div>div>h1"
                }
              ]
            }
          }
        },
        {
          "title": "VIP Hero Block",
          "id": "vip-hero-block",
          "model": "vip-hero-block",
          "plugins": {
            "da": {
              "type": "key-value-block",
              "rows": 26,
              "columns": 1,
              "fields": [
                {
                  "name": "memberName",
                  "selector": "div:nth-child(1)>div:nth-child(1)"
                },
                {
                  "name": "memberTagline",
                  "selector": "div:nth-child(2)>div:nth-child(1)"
                },
                {
                  "name": "heroNumber",
                  "selector": "div:nth-child(3)>div:nth-child(1)"
                },
                {
                  "name": "headlineLine1",
                  "selector": "div:nth-child(4)>div:nth-child(1)"
                },
                {
                  "name": "headlineLine2",
                  "selector": "div:nth-child(5)>div:nth-child(1)"
                },
                {
                  "name": "headlineLine3",
                  "selector": "div:nth-child(6)>div:nth-child(1)"
                },
                {
                  "name": "postscript",
                  "selector": "div:nth-child(7)>div:nth-child(1)"
                },
                {
                  "name": "description",
                  "selector": "div:nth-child(8)>div:nth-child(1)"
                },
                {
                  "name": "ctaPrimary",
                  "selector": "div:nth-child(9)>div:nth-child(1)>a"
                },
                {
                  "name": "ctaSecondary",
                  "selector": "div:nth-child(10)>div:nth-child(1)>a"
                },
                {
                  "name": "perk1",
                  "selector": "div:nth-child(11)>div:nth-child(1)"
                },
                {
                  "name": "perk2",
                  "selector": "div:nth-child(12)>div:nth-child(1)"
                },
                {
                  "name": "perk3",
                  "selector": "div:nth-child(13)>div:nth-child(1)"
                },
                {
                  "name": "perk4",
                  "selector": "div:nth-child(14)>div:nth-child(1)"
                },
                {
                  "name": "dashboardEyebrow",
                  "selector": "div:nth-child(15)>div:nth-child(1)"
                },
                {
                  "name": "dashboardSubline",
                  "selector": "div:nth-child(16)>div:nth-child(1)"
                },
                {
                  "name": "metric1",
                  "selector": "div:nth-child(17)>div:nth-child(1)"
                },
                {
                  "name": "metric2",
                  "selector": "div:nth-child(18)>div:nth-child(1)"
                },
                {
                  "name": "metric3",
                  "selector": "div:nth-child(19)>div:nth-child(1)"
                },
                {
                  "name": "order1",
                  "selector": "div:nth-child(20)>div:nth-child(1)"
                },
                {
                  "name": "order2",
                  "selector": "div:nth-child(21)>div:nth-child(1)"
                },
                {
                  "name": "order3",
                  "selector": "div:nth-child(22)>div:nth-child(1)"
                },
                {
                  "name": "footerItem1",
                  "selector": "div:nth-child(23)>div:nth-child(1)"
                },
                {
                  "name": "footerItem2",
                  "selector": "div:nth-child(24)>div:nth-child(1)"
                },
                {
                  "name": "footerItem3",
                  "selector": "div:nth-child(25)>div:nth-child(1)"
                },
                {
                  "name": "footerRightText",
                  "selector": "div:nth-child(26)>div:nth-child(1)"
                }
              ]
            }
          }
        },
        {
          "title": "VIP Hero MCCS",
          "id": "vip-hero-mccs",
          "model": "vip-hero-mccs",
          "plugins": {
            "da": {
              "type": "key-value-block"
            }
          }
        },
        {
          "title": "How It Works + Stats",
          "id": "how-it-works-stats",
          "model": "how-it-works-stats",
          "plugins": {
            "da": {
              "rows": 12,
              "columns": 1,
              "fields": [
                {
                  "name": "tag",
                  "selector": "div:nth-child(1)>div:nth-child(1)"
                },
                {
                  "name": "title",
                  "selector": "div:nth-child(2)>div:nth-child(1)"
                },
                {
                  "name": "step1",
                  "selector": "div:nth-child(3)>div:nth-child(1)"
                },
                {
                  "name": "step2",
                  "selector": "div:nth-child(4)>div:nth-child(1)"
                },
                {
                  "name": "step3",
                  "selector": "div:nth-child(5)>div:nth-child(1)"
                },
                {
                  "name": "step4",
                  "selector": "div:nth-child(6)>div:nth-child(1)"
                },
                {
                  "name": "stat1",
                  "selector": "div:nth-child(7)>div:nth-child(1)"
                },
                {
                  "name": "stat2",
                  "selector": "div:nth-child(8)>div:nth-child(1)"
                },
                {
                  "name": "stat3",
                  "selector": "div:nth-child(9)>div:nth-child(1)"
                },
                {
                  "name": "stat4",
                  "selector": "div:nth-child(10)>div:nth-child(1)"
                },
                {
                  "name": "buttonPrimary",
                  "selector": "div:nth-child(11)>div:nth-child(1)>a"
                },
                {
                  "name": "buttonSecondary",
                  "selector": "div:nth-child(12)>div:nth-child(1)>a"
                }
              ]
            }
          }
        },
        {
          "title": "How It Works + Stats 2",
          "id": "how-it-works-stats-2",
          "model": "how-it-works-stats-2",
          "plugins": {
            "da": {
              "rows": 12,
              "columns": 1,
              "fields": [
                {
                  "name": "tag",
                  "selector": "div:nth-child(1)>div:nth-child(1)"
                },
                {
                  "name": "title",
                  "selector": "div:nth-child(2)>div:nth-child(1)"
                },
                {
                  "name": "step1",
                  "selector": "div:nth-child(3)>div:nth-child(1)"
                },
                {
                  "name": "step2",
                  "selector": "div:nth-child(4)>div:nth-child(1)"
                },
                {
                  "name": "step3",
                  "selector": "div:nth-child(5)>div:nth-child(1)"
                },
                {
                  "name": "step4",
                  "selector": "div:nth-child(6)>div:nth-child(1)"
                },
                {
                  "name": "stat1",
                  "selector": "div:nth-child(7)>div:nth-child(1)"
                },
                {
                  "name": "stat2",
                  "selector": "div:nth-child(8)>div:nth-child(1)"
                },
                {
                  "name": "stat3",
                  "selector": "div:nth-child(9)>div:nth-child(1)"
                },
                {
                  "name": "stat4",
                  "selector": "div:nth-child(10)>div:nth-child(1)"
                },
                {
                  "name": "buttonPrimary",
                  "selector": "div:nth-child(11)>div:nth-child(1)>a"
                },
                {
                  "name": "buttonSecondary",
                  "selector": "div:nth-child(12)>div:nth-child(1)>a"
                }
              ]
            }
          }
        },
        {
          "title": "Targeted Block",
          "id": "targeted-block",
          "model": "targeted-block",
          "plugins": {
            "da": {
              "type": "key-value-block"
            }
          }
        },
        {
          "title": "Customer Segment Personalization Block",
          "id": "customer-segment-personalization-block",
          "model": "customer-segment-personalization-block",
          "plugins": {
            "da": {
              "type": "key-value-block"
            }
          }
        },
        {
          "title": "Live Block",
          "id": "live-block",
          "model": "live-block",
          "plugins": {
            "da": {
              "type": "key-value-block"
            }
          }
        },
        {
          "title": "Live Block Premium",
          "id": "live-block-premium",
          "model": "live-block-premium",
          "plugins": {
            "da": {
              "type": "key-value-block"
            }
          }
        },
        {
          "title": "VIP Member Block",
          "id": "vip-member-block",
          "model": "vip-member-block",
          "plugins": {
            "da": {
              "name": "vip-member-block",
              "rows": 39,
              "columns": 1,
              "fields": [
                {
                  "name": "eyebrowText",
                  "selector": "div:nth-child(1)>div:nth-child(1)"
                },
                {
                  "name": "title",
                  "selector": "div:nth-child(2)>div:nth-child(1)"
                },
                {
                  "name": "subtitle",
                  "selector": "div:nth-child(3)>div:nth-child(1)"
                },
                {
                  "name": "stat1",
                  "selector": "div:nth-child(4)>div:nth-child(1)"
                },
                {
                  "name": "stat2",
                  "selector": "div:nth-child(5)>div:nth-child(1)"
                },
                {
                  "name": "stat3",
                  "selector": "div:nth-child(6)>div:nth-child(1)"
                },
                {
                  "name": "featuredLabel",
                  "selector": "div:nth-child(7)>div:nth-child(1)"
                },
                {
                  "name": "featuredDiscount",
                  "selector": "div:nth-child(8)>div:nth-child(1)"
                },
                {
                  "name": "featuredCategory",
                  "selector": "div:nth-child(9)>div:nth-child(1)"
                },
                {
                  "name": "featuredTitle",
                  "selector": "div:nth-child(10)>div:nth-child(1)"
                },
                {
                  "name": "featuredDesc",
                  "selector": "div:nth-child(11)>div:nth-child(1)"
                },
                {
                  "name": "featuredPrice",
                  "selector": "div:nth-child(12)>div:nth-child(1)"
                },
                {
                  "name": "featuredCtaPrimary",
                  "selector": "div:nth-child(13)>div:nth-child(1)>a"
                },
                {
                  "name": "featuredCtaSecondary",
                  "selector": "div:nth-child(14)>div:nth-child(1)>a"
                },
                {
                  "name": "benefit1",
                  "selector": "div:nth-child(15)>div:nth-child(1)"
                },
                {
                  "name": "benefit2",
                  "selector": "div:nth-child(16)>div:nth-child(1)"
                },
                {
                  "name": "benefit3",
                  "selector": "div:nth-child(17)>div:nth-child(1)"
                },
                {
                  "name": "benefit4",
                  "selector": "div:nth-child(18)>div:nth-child(1)"
                },
                {
                  "name": "spotlightLabel",
                  "selector": "div:nth-child(19)>div:nth-child(1)"
                },
                {
                  "name": "spotlightCount",
                  "selector": "div:nth-child(20)>div:nth-child(1)"
                },
                {
                  "name": "spotlightItem1",
                  "selector": "div:nth-child(21)>div:nth-child(1)"
                },
                {
                  "name": "spotlightItem2",
                  "selector": "div:nth-child(22)>div:nth-child(1)"
                },
                {
                  "name": "spotlightItem3",
                  "selector": "div:nth-child(23)>div:nth-child(1)"
                },
                {
                  "name": "spotlightFooterText",
                  "selector": "div:nth-child(24)>div:nth-child(1)"
                },
                {
                  "name": "spotlightFooterLink",
                  "selector": "div:nth-child(25)>div:nth-child(1)>a"
                },
                {
                  "name": "accountName",
                  "selector": "div:nth-child(26)>div:nth-child(1)"
                },
                {
                  "name": "accountOrg",
                  "selector": "div:nth-child(27)>div:nth-child(1)"
                },
                {
                  "name": "metric1",
                  "selector": "div:nth-child(28)>div:nth-child(1)"
                },
                {
                  "name": "metric2",
                  "selector": "div:nth-child(29)>div:nth-child(1)"
                },
                {
                  "name": "metric3",
                  "selector": "div:nth-child(30)>div:nth-child(1)"
                },
                {
                  "name": "metric4",
                  "selector": "div:nth-child(31)>div:nth-child(1)"
                },
                {
                  "name": "action1",
                  "selector": "div:nth-child(32)>div:nth-child(1)"
                },
                {
                  "name": "action2",
                  "selector": "div:nth-child(33)>div:nth-child(1)"
                },
                {
                  "name": "action3",
                  "selector": "div:nth-child(34)>div:nth-child(1)"
                },
                {
                  "name": "proof1",
                  "selector": "div:nth-child(35)>div:nth-child(1)"
                },
                {
                  "name": "proof2",
                  "selector": "div:nth-child(36)>div:nth-child(1)"
                },
                {
                  "name": "proof3",
                  "selector": "div:nth-child(37)>div:nth-child(1)"
                },
                {
                  "name": "proofCtaPrimary",
                  "selector": "div:nth-child(38)>div:nth-child(1)>a"
                },
                {
                  "name": "proofCtaSub",
                  "selector": "div:nth-child(39)>div:nth-child(1)"
                }
              ]
            }
          }
        },
        {
          "title": "VIP Member Block Real V2",
          "id": "vip-member-block-real-v2",
          "model": "vip-member-block-real-v2",
          "plugins": {
            "da": {
              "type": "key-value-block"
            }
          }
        },
        {
          "title": "Commerce Account Hub",
          "id": "commerce-account-hub",
          "model": "commerce-account-hub",
          "plugins": {
            "da": {
              "type": "key-value-block"
            }
          }
        },
        {
          "title": "Uniform Configurator",
          "id": "uniform-configurator",
          "model": "uniform-configurator",
          "plugins": {
            "da": {
              "type": "key-value-block"
            }
          }
        },
        {
          "title": "Quiz Router",
          "id": "quiz-router",
          "model": "quiz-router",
          "filter": "quiz-router",
          "plugins": {
            "da": {
              "name": "quiz-router",
              "rows": 1,
              "columns": 3
            }
          }
        },
        {
          "title": "Quiz Router MCCS",
          "id": "quiz-router-mccs",
          "model": "quiz-router-mccs",
          "filter": "quiz-router-mccs",
          "plugins": {
            "da": {
              "name": "quiz-router-mccs",
              "rows": 1,
              "columns": 3
            }
          }
        }
      ]
    },
    {
      "title": "Product",
      "id": "product",
      "components": [
        {
          "title": "Product Configurator Luxe",
          "id": "product-configurator-luxe",
          "model": "product-configurator-luxe",
          "plugins": {
            "da": {
              "type": "key-value-block"
            }
          }
        },
        {
          "title": "Product Details",
          "id": "product-details",
          "model": "product-details",
          "plugins": {
            "da": {
              "type": "key-value-block"
            }
          }
        },
        {
          "title": "Product Highlights",
          "id": "product-highlights",
          "model": "product-highlights",
          "plugins": {
            "da": {
              "name": "product-highlights",
              "rows": 4,
              "columns": 2
            }
          }
        },
        {
          "title": "Product Recommendations",
          "id": "product-recommendations",
          "model": "product-recommendations",
          "plugins": {
            "da": {
              "type": "key-value-block"
            }
          }
        },
        {
          "title": "Product Teaser",
          "id": "product-teaser",
          "model": "product-teaser",
          "plugins": {
            "da": {
              "type": "key-value-block"
            }
          }
        },
        {
          "title": "Product Technical Details",
          "id": "product-technical-details",
          "model": "product-technical-details",
          "plugins": {
            "da": {
              "type": "key-value-block"
            }
          }
        }
      ]
    }
  ]
}